{"moduleName":["Data","Ord","Unsafe"],"imports":[{"annotation":{"meta":null,"sourceSpan":{"start":[1,1],"end":[15,6]}},"moduleName":["Data","Ord","Unsafe"]},{"annotation":{"meta":null,"sourceSpan":{"start":[1,1],"end":[15,6]}},"moduleName":["Data","Ordering"]},{"annotation":{"meta":null,"sourceSpan":{"start":[1,1],"end":[15,6]}},"moduleName":["Prim"]}],"builtWith":"0.12.5","modulePath":".psc-package\\psc-0.12.3\\prelude\\v4.1.0\\src\\Data\\Ord\\Unsafe.purs","exports":["unsafeCompare"],"decls":[{"annotation":{"meta":null,"sourceSpan":{"start":[5,1],"end":[5,46]}},"identifier":"unsafeCompare","expression":{"annotation":{"meta":null,"sourceSpan":{"start":[6,17],"end":[6,43]}},"argument":{"annotation":{"meta":{"metaType":"IsConstructor","identifiers":[],"constructorType":"SumType"},"sourceSpan":{"start":[6,41],"end":[6,43]}},"value":{"moduleName":["Data","Ordering"],"identifier":"GT"},"type":"Var"},"type":"App","abstraction":{"annotation":{"meta":null,"sourceSpan":{"start":[6,17],"end":[6,43]}},"argument":{"annotation":{"meta":{"metaType":"IsConstructor","identifiers":[],"constructorType":"SumType"},"sourceSpan":{"start":[6,38],"end":[6,40]}},"value":{"moduleName":["Data","Ordering"],"identifier":"EQ"},"type":"Var"},"type":"App","abstraction":{"annotation":{"meta":null,"sourceSpan":{"start":[6,17],"end":[6,43]}},"argument":{"annotation":{"meta":{"metaType":"IsConstructor","identifiers":[],"constructorType":"SumType"},"sourceSpan":{"start":[6,35],"end":[6,37]}},"value":{"moduleName":["Data","Ordering"],"identifier":"LT"},"type":"Var"},"type":"App","abstraction":{"annotation":{"meta":{"metaType":"IsForeign"},"sourceSpan":{"start":[6,17],"end":[6,34]}},"value":{"moduleName":["Data","Ord","Unsafe"],"identifier":"unsafeCompareImpl"},"type":"Var"}}}},"bindType":"NonRec"}],"comments":[],"foreign":["unsafeCompareImpl"],"sourceSpan":{"start":[1,1],"end":[15,6]}}